CwnGraph/__init__.py
CwnGraph/cwnDot.py
CwnGraph/cwn_base.py
CwnGraph/cwn_graph.py
CwnGraph/cwn_graph_utils.py
CwnGraph/cwn_sql_template.py
CwnGraph/cwn_stat.py
CwnGraph/cwnio.py
CwnGraph/download.py
CwnGraph/helper_CwnGraphUtils.py
CwnGraph/cwn_types/__init__.py
CwnGraph/cwn_types/cwn_node_types.py
CwnGraph/cwn_types/cwn_relation_types.py
CwnGraph/cwn_types/cwn_types.py
CwnGraph/cwn_types/labels.py
CwnGraph-0.4.0.dist-info/LICENSE
CwnGraph-0.4.0.dist-info/METADATA
CwnGraph-0.4.0.dist-info/WHEEL
CwnGraph-0.4.0.dist-info/top_level.txt
CwnGraph-0.4.0.dist-info/RECORD
